MANIFEST.in
README.txt
setup.py
eusful/__init__.py
eusful.egg-info/PKG-INFO
eusful.egg-info/SOURCES.txt
eusful.egg-info/dependency_links.txt
eusful.egg-info/top_level.txt
eusful/data/__init__.py
eusful/decorators/__init__.py
eusful/errors/__init__.py
eusful/for_web/__init__.py
eusful/xpath/__init__.py