Metadata-Version: 1.0
Name: eusful
Version: 0.7.2
Summary: These are things I use in places.
Home-page: UNKNOWN
Author: Eugene Efremov
Author-email: eaefremov@gmail.com
License: MIT
Platform: UNKNOWN
